discord/ext/ipc/__init__.py
discord/ext/ipc/client.py
discord/ext/ipc/errors.py
discord/ext/ipc/server.py
discord_next_ipc-2.1.3.dist-info/LICENSE
discord_next_ipc-2.1.3.dist-info/METADATA
discord_next_ipc-2.1.3.dist-info/WHEEL
discord_next_ipc-2.1.3.dist-info/top_level.txt
discord_next_ipc-2.1.3.dist-info/RECORD
