Metadata-Version: 2.1
Name: discord-next-ipc
Version: 2.1.3
Summary: A discord.py extension for inter-process communication. Continued by Alex Hutz.
Home-page: https://github.com/FrostiiWeeb/discord-next-ipc
Author: Alex Hutz
License: Apache Software License
Project-URL: Documentation, https://discord-ext-ipc.readthedocs.io
Project-URL: Issue Tracker, https://github.com/FrostiiWeeb/discord-next-ipc/issues
Project-URL: Source, https://github.com/FrostiiWeeb/discord-next-ipc
Platform: UNKNOWN
Classifier: Development Status :: 5 - Production/Stable
Classifier: Framework :: AsyncIO
Classifier: Intended Audience :: Developers
Classifier: License :: OSI Approved :: Apache Software License
Classifier: Natural Language :: English
Classifier: Operating System :: OS Independent
Classifier: Programming Language :: Python
Classifier: Programming Language :: Python :: 3
Classifier: Programming Language :: Python :: 3 :: Only
Classifier: Programming Language :: Python :: 3.5
Classifier: Programming Language :: Python :: 3.6
Classifier: Programming Language :: Python :: 3.7
Classifier: Programming Language :: Python :: 3.8
Classifier: Programming Language :: Python :: 3.9
Classifier: Programming Language :: Python :: 3.10
Classifier: Programming Language :: Python :: Implementation :: CPython
Classifier: Topic :: Communications
Classifier: Topic :: Documentation
Classifier: Topic :: Documentation :: Sphinx
Classifier: Topic :: Internet
Classifier: Topic :: Software Development
Classifier: Topic :: Software Development :: Libraries
Classifier: Topic :: Software Development :: Libraries :: Python Modules
Requires-Python: >=3.8.0
License-File: LICENSE
Requires-Dist: discord.py
Requires-Dist: fastapi
Requires-Dist: uvicorn
Requires-Dist: unsync
Requires-Dist: uvloop
Provides-Extra: docs
Requires-Dist: sphinx ; extra == 'docs'
Requires-Dist: sphinxcontrib-trio ; extra == 'docs'
Requires-Dist: sphinx-rtd-theme ; extra == 'docs'
